[{"dept": "機械工学科", "labs": [{"keywords": ["キャビテーション", "マイクロバブル", "ウォータジェット", "流体力学"], "lab": "佐藤・杉本研究室"}, {"keywords": ["形状記憶合金", "応力誘起変態", "新材料"], "lab": "矢島・岸研究室"}, {"keywords": ["コンピュータシミュレーション", "自動車", "事前予測技術"], "lab": "山部昌研究室"}, {"keywords": ["カスタムメイド", "医療・福祉", "人工関節", "骨再生"], "lab": "新谷一博研究室"}, {"keywords": ["合金設計", "計算材料学", "インプラント", "水素脆性"], "lab": "高野則之研究室"}, {"keywords": ["太陽電池", "電力用半導体素子（パワーデバイス）", "超精密加工", "切断・研磨加工", "振動援用加工"], "lab": "諏訪部仁研究室"}, {"keywords": ["複合材料", "長期耐久性", "輸送機械", "インフラ構造物"], "lab": "中田政之研究室"}, {"keywords": ["高速運動制御", "工作機械", "ナノ", "CAMシステム"], "lab": "森本喜隆研究室"}, {"keywords": ["切削加工", "高能率・高精度", "新素材", "微細加工技術"], "lab": "加藤秀治研究室"}, {"keywords": ["燃焼・伝熱現象計測", "光学計測", "機械機構メカニズム", "電磁誘導現象", "エネルギー回生"], "lab": "十河憲夫研究室"}, {"keywords": ["超精密加工", "化学機械研磨", "音響・画像計測", "遠隔監視システム", "生産原論"], "lab": "畝田道雄研究室"}, {"keywords": ["複合材料", "材料機能創製", "計算力学", "バイオマテリアル", "バイオメカニクス"], "lab": "田中基嗣研究室"}, {"keywords": ["エネルギー変換", "次世代パワートレイン", "水素", "エンジン"], "lab": "長沼要研究室"}, {"keywords": ["塑性加工学", "生産工学", "数値解析"], "lab": "瀬川明夫研究室"}, {"keywords": ["複合材料（FRP）", "ものづくり", "成形", "破壊", "信頼性"], "lab": "斉藤博嗣研究室"}, {"keywords": ["小温度差熱エネルギーの移動促進と利用", "電場を利用した熱・物質移動の促進と制御", "熱物性", "太陽エネルギーの集熱と利用", "過冷却状態の維持と解消"], "lab": "藤本雅則研究室"}, {"keywords": ["ものづくり", "成形プロセス", "プロセスシミュレーション", "予測技術", "金型技術"], "lab": "瀬戸雅宏研究室"}, {"keywords": ["生産工学", "機械加工", "ＮＣ工作機械の省エネ化", "生産活動のＩｏＴ化", "３Ｄプリンタの活用・開発"], "lab": "林晃生研究室"}, {"keywords": ["流体工学", "伝熱工学", "生体模倣（バイオミメティクス）", "脈を打つ流れ", "ものづくりにおける熱流体設計"], "lab": "福江高志研究室"}]}, {"dept": "航空システム工学科", "labs": [{"keywords": ["ジェットエンジン", "ガスタービン", "高効率・環境適合エンジン"], "lab": "藤・土屋研究室"}, {"keywords": ["超小型無人飛行機", "羽ばたき翼", "風洞実験", "シミュレーション"], "lab": "岡本正人研究室"}, {"keywords": ["炭素繊維強化プラスチック", "複合材料", "革新的構造の追究", "環境に優しい航空機"], "lab": "廣瀬・吉田研究室"}, {"keywords": ["航空材料", "機能向上（機械的・化学的・電気的）", "表面処理"], "lab": "小栗和幸研究室"}, {"keywords": ["社会貢献", "飛行安全", "飛行制御システム", "シミュレータ"], "lab": "橋本和典研究室"}, {"keywords": ["数値流体力学", "空力解析", "設計最適化手法", "航空機の環境適合性向上"], "lab": "佐々木大輔研究室"}, {"keywords": ["小型無人航空機", "ドローン", "パラシュート", "コンパウンドヘリコプタ"], "lab": "赤坂剛史研究室"}]}, {"dept": "ロボティクス学科", "labs": [{"keywords": ["生活支援ロボット", "自律移動ロボット", "ロボカップ"], "lab": "出村公成研究室"}, {"keywords": ["センサ", "実世界情報処理", "生活支援"], "lab": "小暮潔研究室"}, {"keywords": ["制御工学", "ロボティクス", "生活支援技術", "福祉医療支援技術"], "lab": "鈴木亮一研究室"}, {"keywords": ["水中センシング", "水中ロボット", "音響通信・信号処理"], "lab": "太田和彦研究室"}, {"keywords": ["ロボット用嗅覚センサ", "筋電義手", "生活支援ロボット", "二足歩行ロボット", "農業支援ロボット"], "lab": "竹井義法研究室"}, {"keywords": ["ヒューマンモーションコントロール", "機能的電気刺激", "リハビリシステム", "ロボット制御"], "lab": "河合宏之研究室"}, {"keywords": ["遠隔操作", "ロボットハンド"], "lab": "藤木信彰研究室"}, {"keywords": ["多脚ロボット", "不整地移動", "災害対応", "持続可能社会"], "lab": "土居隆宏研究室"}, {"keywords": ["ハードウェア", "ソフトウェア", "センサ", "ロボット"], "lab": "平澤一樹研究室"}, {"keywords": ["ロボット制御", "視覚フィードバック", "医療ロボティクス", "エネルギーマネジメント"], "lab": "村尾俊幸研究室"}]}, {"dept": "電気電子工学科", "labs": [{"keywords": ["3D画像", "3Dディスプレイ", "LED照明用駆動回路"], "lab": "坂本康正研究室"}, {"keywords": ["環境無害型絶縁油の開発と電気絶縁評価", "電気・磁気レオロジー流体開発と応用技術", "低周波公害問題", "電気流体力学（EHD）と液体応用技術"], "lab": "花岡良一研究室"}, {"keywords": ["有機EL", "フレキシブルディスプレイ"], "lab": "三上明義研究室"}, {"keywords": ["ナノ構造体", "エネルギー変換材料", "環境調和型社会の実現"], "lab": "前田正彦研究室"}, {"keywords": ["計測制御対象の電子回路の設計・製作", "生物との会話", "植物工場・茸工場などの人工栽培", "光線利用による害虫防除"], "lab": "平間淳司研究室"}, {"keywords": ["移動通信", "衛星通信", "マイクロ波回路"], "lab": "廣田哲夫研究室"}, {"keywords": ["モータ", "発電機", "電気自動車", "ハイブリッド電気自動車", "風力発電"], "lab": "深見・津田研究室"}, {"keywords": ["ナノテクノロジー", "量子デバイスプロセス制御", "ナノマシン", "高品質中性フリーラジカルビーム"], "lab": "林啓治研究室"}, {"keywords": ["太陽電池", "次世代型高変換効率デバイス", "亜酸化銅（Cu2O)", "ディスプレイ", "センサー"], "lab": "宮田俊弘研究室"}, {"keywords": ["ＬＥＤ（発光ダイオード）", "レーザ", "半導体"], "lab": "山口敦史研究室"}, {"keywords": ["音響工学", "オーディオシステム", "音響物理学"], "lab": "青木茂明研究室"}, {"keywords": ["アンテナ", "メタマテリアル", "リフレクトアレー", "ＩＯＴ用アンテナ", "衛星搭載用アンテナ"], "lab": "牧野滋研究室"}, {"keywords": ["高電圧／放電応用", "高輝度パルスレーザ", "センサ／センシングデバイス", "医用超音波", "物理的遺伝子導入／細胞加工"], "lab": "會澤康治研究室"}, {"keywords": ["シリコン半導体デバイス", "集積回路", "超省電力デバイス"], "lab": "井田次郎研究室"}, {"keywords": ["無線通信", "マイクロ波回路", "無線電力伝送"], "lab": "伊東健治研究室"}, {"keywords": ["小形アンテナ", "環境発電", "移動通信", "スマートフォン／無線LAN", "電波伝搬"], "lab": "野口啓介研究室"}, {"keywords": ["超高電圧", "放電抑制技術", "次世代電力機器開発", "電力流通ネットワーク"], "lab": "宮城克徳研究室"}, {"keywords": ["蓄電技術リテラシー", "蓄電デバイス", "充放電制御", "蓄電システム", "安全性・信頼性技術"], "lab": "漆畑・藤田・河野研究室"}, {"keywords": ["電力変換回路技術", "モータ制御／モーション制御", "ワイヤレス給電システム", "バッテリーの充放電システム", "風力発電システム／太陽光発電システム"], "lab": "小山正人研究室"}, {"keywords": ["IoTシステム", "通信プロトコル", "ネットワーク仮想化", "トラヒック解析"], "lab": "横谷哲也研究室"}, {"keywords": ["次世代パワー半導体", "電気機器の省エネ", "性能限界評価技術"], "lab": "中田修平研究室"}, {"keywords": ["電力・エネルギーシステム", "スマートグリッドシステム", "エネルギーマネージメントシステム"], "lab": "泉井良夫研究室"}, {"keywords": ["音響信号処理", "適応制御", "機械学習", "数理モデル"], "lab": "島内末廣研究室"}, {"keywords": ["大気圧プラズマ", "プラズマ化学", "大気汚染防止技術", "活性種（オゾン・ラジカル）", "エネルギー分野（高電圧絶縁・大電流遮断）"], "lab": "大澤直樹研究室"}, {"keywords": ["蛍光体", "発光デバイス", "次世代照明", "省資源・省エネルギー", "ナノ材料"], "lab": "深田晴己研究室"}, {"keywords": ["ナノテクノロジー", "高感度センシング", "高精度空間制御", "原子・分子の観察・識別・操作", "顕微・分光装置の新規開発"], "lab": "芦野慎研究室"}, {"keywords": ["プラズマ", "機能性薄膜", "ダイアモンドライクカーボン", "フィジカルセンサ", "プラズマ滅菌"], "lab": "池永訓昭研究室"}, {"keywords": ["意図的・記号的コミュニケーション", "文脈依存型情報伝送", "知識共創", "認知科学"], "lab": "金野武司研究室"}, {"keywords": ["計測制御", "生体情報", "植物工場", "生体との対話", "自然との共生"], "lab": "柳橋秀幸研究室"}]}, {"dept": "情報工学科", "labs": [{"keywords": ["並列処理技術", "PCクラスタ", "分散型並列計算機"], "lab": "津田伸生研究室"}, {"keywords": ["セキュリティ", "教育アプリ", "不正アクセス", "不正侵入", "サイバー攻撃検知"], "lab": "五十嵐寛研究室"}, {"keywords": ["自然計算", "量子コンピュータ", "分子コンピュータ", "粘菌", "アメーバ"], "lab": "蜷川繁研究室"}, {"keywords": ["ロボット", "画像処理技術", "センサーネットワーク"], "lab": "中沢実研究室"}, {"keywords": ["知能情報処理", "パターン認識／人工知能", "情報統合／センサフュージョン", "パーソナル知能ロボット", "マルチメディア検索・マイニングシステム"], "lab": "長田茂美研究室"}, {"keywords": ["ビッグデータ", "データサイエンス", "機械学習", "ディープラーニング"], "lab": "中野淳研究室"}, {"keywords": ["コンピュータグラフィックス(CG)", "プロジェクションマッピング", "ゲーム", "画像処理(IM)", "バーチャルリアリティ"], "lab": "郭清蓮研究室"}, {"keywords": ["コミュニケーション", "ヒューマンインタフェース", "VR・AR", "ユーザエクスペリエンス", "AI・ビックデータ"], "lab": "山本知仁研究室"}, {"keywords": ["自然言語理解／生成", "人工知能", "センサー", "人と機械の対話", "言葉と数値"], "lab": "松井くにお研究室"}, {"keywords": ["通信方式", "ネットワークセキュリティ", "組み込みシステム", "IoT"], "lab": "向井宏明研究室"}, {"keywords": ["情報システムの設計・構築・評価", "次世代に適応できる情報基盤", "システムの安定化、信頼性向上", "プログラミング言語の活用", "データ構造の解析と変換"], "lab": "黒瀨浩研究室"}, {"keywords": ["ソーシャルメディア", "ツイッター", "Web情報学"], "lab": "阿部倫之研究室"}, {"keywords": ["アルゴリズム", "計算量", "データマイニング"], "lab": "元木光雄研究室"}, {"keywords": ["組込みシステム", "農業ICT", "介護福祉ロボット", "見守り玩具", "教材開発"], "lab": "河並崇研究室"}, {"keywords": ["シミュレーション", "データマイニング", "高性能計算", "可視化"], "lab": "林亮子研究室"}, {"keywords": ["情報圧縮技術", "組込みシステム", "Linux"], "lab": "鷹合大輔研究室"}, {"keywords": ["実世界コンピューティング", "ウェアラブルコンピューティング", "ユビキタスコンピューティング", "エンターテインメントコンピューティング"], "lab": "佐野渉二研究室"}]}, {"dept": "環境土木工学科", "labs": [{"keywords": ["自然災害", "地盤災害", "地域防災計画"], "lab": "川村國夫研究室"}, {"keywords": ["環境", "木材", "構造工学", "維持管理工学"], "lab": "本田秀行研究室"}, {"keywords": ["地盤沈下", "地盤変形予測"], "lab": "外崎明研究室"}, {"keywords": ["準天頂衛星システム", "地理情報システム（電子地図）", "各種GNSSの有効活用", "地上レーザー計測", "サイエンスセミナー（カメリアキッズ）"], "lab": "鹿田正昭研究室"}, {"keywords": ["トンネル工学", "地下空間維持管理", "アセットマネジメント"], "lab": "木村定雄研究室"}, {"keywords": ["地球環境・地域環境", "街路樹・農地の植生モニタリング", "リモートセンシング・電子地図", "3次元都市モデル", "構造物のメンテナンス"], "lab": "徳永光晴研究室"}, {"keywords": ["環境", "コンクリート長寿命化", "維持管理", "エコマテリアル", "安全・安心材料"], "lab": "宮里心一研究室"}, {"keywords": ["海岸工学", "海岸モニタリング", "離岸流", "アマモ場造成"], "lab": "有田守研究室"}, {"keywords": ["防災", "構造解析", "耐震構造", "メンテナンス", "非破壊検査"], "lab": "田中泰司研究室"}, {"keywords": ["防災", "維持管理工学（メンテナンス工学）", "構造物の補修・補強", "建設材料学", "コンクリート工学"], "lab": "花岡大伸研究室"}]}, {"dept": "メディア情報学科", "labs": [{"keywords": ["ゲーム・アニメと人の感情", "「萌え」の科学", "メディア・コンテンツの設計科学", "エンタテイメント工学"], "lab": "山田真司研究室"}, {"keywords": ["映像メディア", "学習システム", "教育システム", "CG", "コミュニケーション"], "lab": "鎌田洋研究室"}, {"keywords": ["ネットワークセキュリティ", "コンピュータウイルス対策", "不正アクセス対策"], "lab": "千石靖研究室"}, {"keywords": ["ビジュアル・インフォメーション・デザイン", "メディアデザイン", "視覚文化研究"], "lab": "出原立子研究室"}, {"keywords": ["高臨場感通信", "コミュニケーション", "拡張現実", "情報ディスプレイ"], "lab": "中沢憲二研究室"}, {"keywords": ["Webサイト", "プロモーションビデオ", "視線データ", "映像の心理学", "データ解析"], "lab": "松下裕研究室"}, {"keywords": ["情報発信", "ICTと人間・社会"], "lab": "山岸芳夫研究室"}, {"keywords": ["音楽情報処理、音楽心理", "作編曲、演奏、音楽・和声の印象評定", "音楽コンテンツの設計"], "lab": "江村伯夫研究室"}, {"keywords": ["メディア音声", "音声生体情報", "MRI(磁気共鳴画像)・センサ", "VR・AR・3D", "伝わる音声・英語・アニメ声"], "lab": "高野佐代子研究室"}, {"keywords": ["視覚デザイン", "色彩工学", "脳情報学", "バーチャルリアリティ"], "lab": "根岸一平研究室"}, {"keywords": ["ヒューマンライフデザイン", "エンタテインメントコンピューティング", "芸術科学"], "lab": "浦正広研究室"}, {"keywords": ["医用画像", "画像解析", "グラフィックス", "プログラミング", "CT、MRI"], "lab": "坂知樹研究室"}]}, {"dept": "経営情報学科", "labs": [{"keywords": ["企業会計", "経営分析", "簿記", "コーポレートファイナンス", "データ分析・フィールドワーク"], "lab": "倉島千徳研究室"}, {"keywords": ["データサイエンス", "オープンデータ活用", "教育工学", "シミュレーション工学", "社会システム工学"], "lab": "武市祥司研究室"}, {"keywords": ["セキュリティ", "ビジネスモデル", "安全・安心"], "lab": "勝山光太郎研究室"}, {"keywords": ["起業・新規事業開発", "地域共創（CSV）", "海外事業開発", "化学品・化粧品事業開発", "環境・インフラ事業開発"], "lab": "松林賢司研究室"}, {"keywords": ["高度交通システム", "スマートコミュニティ", "エネルギーマネジメント", "モノのインターネット(IoT)", "オープンイノベーション"], "lab": "齋藤正史研究室"}, {"keywords": ["経営工学", "統計解析", "多変量解析", "地理情報システム（GIS)"], "lab": "石原正彦研究室"}, {"keywords": ["グローバル経営", "SDGs/BoP/ソーシャルビジネス", "地方創生", "国際開発", "リーダーシップ"], "lab": "平本督太郎研究室"}, {"keywords": ["企業会計", "組織再編", "M&A", "税務", "会社法"], "lab": "北川達也研究室"}]}, {"dept": "心理科学科", "labs": [{"keywords": ["認知と感性の心理学", "感性脳科学", "NIRS"], "lab": "近江政雄研究室"}, {"keywords": ["ものづくり心理学", "感性工学", "ヒューマンインタフェース", "製品開発"], "lab": "神宮英夫研究室"}, {"keywords": ["臨床心理学", "発達支援", "カウンセリング"], "lab": "石川健介研究室"}, {"keywords": ["創造的思考", "アートとデザインの心理学", "認知科学"], "lab": "田中吉史研究室"}, {"keywords": ["心理学実験", "脳機能測定", "視線計測実験", "コンピュータ", "心の働き"], "lab": "伊丸岡俊秀研究室"}, {"keywords": ["コミュニケーション", "顔", "感情", "ヒューマンインタフェース", "SNS"], "lab": "渡邊伸行研究室"}, {"keywords": ["認知と感情", "パーソナリティ", "感情制御", "精神衛生（メンタルヘルス）"], "lab": "星野貴俊研究室"}, {"keywords": ["感動", "物語", "社会心理学", "感情心理学"], "lab": "加藤樹里研究室"}]}, {"dept": "建築学科", "labs": [{"keywords": ["地理情報システム", "古地図研究", "延焼シミュレーション", "津波火災", "都市動態"], "lab": "増田達男研究室"}, {"keywords": ["才能や個性を活かしたデザイン力", "設計理論の研究", "建築設計競技への出品", "プロジェクトを通した社会貢献"], "lab": "蜂谷俊雄研究室"}, {"keywords": ["歴史的建造物の保存・活用", "文化的遺産", "茅葺き民家"], "lab": "中森勉研究室"}, {"keywords": ["芸術的側面と計画的側面の両立", "美しいもの", "建築設計競技への参加"], "lab": "川﨑寧史研究室"}, {"keywords": ["空間デザイン", "空間情報技術", "BIM", "ITを活かしたものづくり", "地域連携"], "lab": "下川雄一研究室"}, {"keywords": ["ファイナンスによる建物の質的向上", "建材・建築部品のグローバリゼーション", "リノベーションがもたらすインパクト", "耐火性を持つ木造"], "lab": "佐藤考一研究室"}, {"keywords": ["サスティナブルな建築・空間デザイン", "リノベーション・コンバージョン", "学生アパートの再生", "構法デザイン"], "lab": "宮下智裕研究室"}, {"keywords": ["歴史的建築物", "文化財保存", "大工技術", "建築アーカイヴス"], "lab": "山崎幹泰研究室"}, {"keywords": ["建築デザイン", "あたらしい空間と環境の創造"], "lab": "竹内申一研究室"}, {"keywords": ["景観工学", "ランドスケープ・アーキテクチュア", "都市デザイン", "都市・地域計画", "まちづくり"], "lab": "山田圭二郎研究室"}, {"keywords": ["建築史", "近代建築", "現代建築", "建築アーカイヴス"], "lab": "戸田穣研究室"}, {"keywords": ["自然エネルギー活用建築", "太陽・光・雨・風・緑・土"], "lab": "垂水弘夫研究室"}, {"keywords": ["空気環境", "空調・換気", "延焼火災"], "lab": "永野紳一郎研究室"}, {"keywords": ["環境心理", "サウンドスケープ", "サイン音", "認知構造"], "lab": "土田義郎研究室"}, {"keywords": ["木造建築", "長持ちする建築", "リサイクル・リユース"], "lab": "後藤正美研究室"}, {"keywords": ["建物が崩壊する仕組み", "形と力のデザイン"], "lab": "西村督研究室"}, {"keywords": ["付加価値の向上", "耐震工学", "免震構造／制震構造", "地震リスク", "環境振動／地盤震動"], "lab": "山岸邦彰研究室"}, {"keywords": ["都市熱環境", "建築環境設計", "緑の活用", "ヒートアイランド"], "lab": "円井基史研究室"}, {"keywords": ["建築構法", "構造計画", "建築材料"], "lab": "須田達研究室"}, {"keywords": ["木質構造", "地震被害とシミュレーション", "まちなみの耐震化"], "lab": "佐藤弘美研究室"}]}, {"dept": "応用化学科", "labs": [{"keywords": ["スパッタリング", "薄膜物性", "太陽電池", "光学薄膜"], "lab": "草野英二研究室"}, {"keywords": ["生分解性プラスチック", "食品化学", "化粧品", "医用材料", "健康素材"], "lab": "大澤敏研究室"}, {"keywords": ["溶媒抽出法", "レアメタルの分離回収", "水環境の動態調査", "有機無機ハイブリッド吸着剤"], "lab": "藤永薫研究室"}, {"keywords": ["ナノサイエンス", "走査型アトムプロープ", "物質表面での化学と分析"], "lab": "谷口昌宏研究室"}, {"keywords": ["無機材料", "電池", "結晶構造", "プラスチック", "モノを燃えなくする化合物"], "lab": "露本伊佐男研究室"}, {"keywords": ["飲料水", "食品の安全", "殺菌・消毒・抗菌", "微生物燃料電池", "グリーンケミストリー"], "lab": "土佐光司研究室"}, {"keywords": ["機能性高分子", "有機系材料", "環境にやさしい材料", "複合材料"], "lab": "吉村治研究室"}, {"keywords": ["機能性ペプチド", "酵素", "生体機能関連化学", "バイオコンジュゲート", "分子設計"], "lab": "小野慎研究室"}, {"keywords": ["金属イオン吸着材", "金属イオンの選択的分離", "コンクリートの化学的侵食", "コンクリート用表面含浸材"], "lab": "大嶋俊一研究室"}, {"keywords": ["有機合成", "分子鋳型", "機器分析", "分離・吸着", "考古化学"], "lab": "坂本宗明研究室"}, {"keywords": ["生分解性プラスチック", "生物模倣・機能応用", "微生物", "包装資材"], "lab": "谷田育宏研究室"}]}, {"dept": "応用バイオ学科", "labs": [{"keywords": ["感覚", "運動", "認知", "情動", "医工学"], "lab": "河原哲夫研究室"}, {"keywords": ["脳と行動", "神経ホルモン", "進化", "バイオミメティクス", "生命デザイン"], "lab": "長尾隆司研究室"}, {"keywords": ["酵素", "微生物の力", "バイオコンバージョン", "機能性素材"], "lab": "尾関健二研究室"}, {"keywords": ["抗生物質", "抗ガン剤", "バイオフィルム", "バイオリアクター", "カビと放射菌"], "lab": "小田忍研究室"}, {"keywords": ["納豆菌", "海洋性微生物", "腸内細菌", "遺伝子工学", "食糧・環境・エネルギー・医薬"], "lab": "袴田佳宏研究室"}, {"keywords": ["一分子を見る", "分子を光で操作する", "ナノテクノロジー", "スーパーイメージング", "培養脳細胞"], "lab": "辰巳仁史研究室"}, {"keywords": ["糸状菌", "化粧品", "遺伝子組換え", "酵素", "ゲノム解析"], "lab": "佐野元昭研究室"}, {"keywords": ["遺伝情報解析", "オミクス解析", "データマイニング", "バイオデータベース", "分子進化"], "lab": "相良純一研究室"}, {"keywords": ["植物工場", "アグロメディカルフーズ", "機能性野菜", "農業ICT"], "lab": "松本恵子研究室"}]}]